sphinx_reload.py
sphinx_reload-0.2.0.dist-info/LICENSE
sphinx_reload-0.2.0.dist-info/METADATA
sphinx_reload-0.2.0.dist-info/WHEEL
sphinx_reload-0.2.0.dist-info/entry_points.txt
sphinx_reload-0.2.0.dist-info/top_level.txt
sphinx_reload-0.2.0.dist-info/RECORD
