Metadata-Version: 1.1
Name: sphinx-reload
Version: 0.2.0
Summary: Live preview your Sphinx documentation
Home-page: https://github.com/prkumar/sphinx-reload
Author: P. Raj Kumar
Author-email: raj.pritvi.kumar@gmail.com
License: MIT
Keywords: sphinx live preview sync reload documentation
Platform: UNKNOWN
Classifier: Development Status :: 2 - Pre-Alpha
Classifier: Environment :: Console
Classifier: Intended Audience :: Developers
Classifier: License :: OSI Approved :: MIT License
Classifier: Programming Language :: Python :: 2
Classifier: Programming Language :: Python :: 2.7
Classifier: Programming Language :: Python :: 3
Classifier: Programming Language :: Python :: 3.3
Classifier: Programming Language :: Python :: 3.4
Classifier: Programming Language :: Python :: 3.5
Classifier: Programming Language :: Python :: 3.6
Classifier: Programming Language :: Python :: 3.7
Classifier: Topic :: Software Development :: Documentation
